cmspw/__init__.py
cmspw/__main__.py
cmspw/data/kbmap.py
cmspw-1.1.2.dist-info/entry_points.txt
cmspw-1.1.2.dist-info/LICENSE
cmspw-1.1.2.dist-info/WHEEL
cmspw-1.1.2.dist-info/METADATA
cmspw-1.1.2.dist-info/RECORD
