Metadata-Version: 2.1
Name: cmspw
Version: 1.1.2
Summary: generates passwords for CMS
Home-page: https://pypi.org/project/cmspw/
Author: Ryan Delaney
Author-email: ryan@truss.works
Requires-Python: >=3.7,<4.0
Classifier: Programming Language :: Python :: 3
Classifier: Programming Language :: Python :: 3.7
Classifier: Programming Language :: Python :: 3.8
Classifier: Programming Language :: Python :: 3.9
Project-URL: Repository, https://github.com/trussworks/cmspw
